docxmd_converter/__init__.py
docxmd_converter/cli.py
docxmd_converter/core.py
docxmd_converter/enhanced_processor.py
docxmd_converter/gui.py
docxmd_converter/processor.py
docxmd_converter/reporting.py
docxmd_converter-3.0.0.dist-info/licenses/LICENSE
docxmd_converter-3.0.0.dist-info/METADATA
docxmd_converter-3.0.0.dist-info/WHEEL
docxmd_converter-3.0.0.dist-info/entry_points.txt
docxmd_converter-3.0.0.dist-info/top_level.txt
docxmd_converter-3.0.0.dist-info/RECORD
