Metadata-Version: 2.4
Name: docxmd-converter
Version: 3.0.0
Summary: Convert between .docx and .md files with template support and advanced document post-processing
Author-email: we256681 <we256681@gmail.com>
Project-URL: Homepage, https://github.com/we256681/docxmd_converter
Project-URL: Bug Reports, https://github.com/we256681/docxmd_converter/issues
Project-URL: Source, https://github.com/we256681/docxmd_converter
Project-URL: Documentation, https://github.com/we256681/docxmd_converter#readme
Keywords: docx,markdown,converter,pandoc,office,documentation,post-processing,document-cleaning,text-processing
Classifier: Development Status :: 4 - Beta
Classifier: Intended Audience :: Developers
Classifier: Intended Audience :: End Users/Desktop
Classifier: License :: OSI Approved :: MIT License
Classifier: Operating System :: OS Independent
Classifier: Programming Language :: Python :: 3
Classifier: Programming Language :: Python :: 3.8
Classifier: Programming Language :: Python :: 3.9
Classifier: Programming Language :: Python :: 3.10
Classifier: Programming Language :: Python :: 3.11
Classifier: Programming Language :: Python :: 3.12
Classifier: Topic :: Office/Business :: Office Suites
Classifier: Topic :: Text Processing :: Markup
Classifier: Topic :: Utilities
Requires-Python: >=3.8
License-File: LICENSE
Requires-Dist: pypandoc>=1.11
Requires-Dist: python-docx>=0.8.11
Provides-Extra: dev
Requires-Dist: pytest>=7.0; extra == "dev"
Requires-Dist: pytest-cov>=4.0; extra == "dev"
Requires-Dist: black>=22.0; extra == "dev"
Requires-Dist: isort>=5.0; extra == "dev"
Requires-Dist: flake8>=6.0; extra == "dev"
Requires-Dist: mypy>=1.0; extra == "dev"
Requires-Dist: bump2version>=1.0; extra == "dev"
Requires-Dist: twine>=4.0; extra == "dev"
Requires-Dist: build>=0.10; extra == "dev"
Requires-Dist: pre-commit>=3.0; extra == "dev"
Dynamic: license-file
